<?xml version="1.0" encoding="UTF-8"?>
<AccessControlPolicy xmlns="http://s3.amazonaws.com/doc/2006-03-01/">
  <Owner>
    <ID>1f0889cd34796acfd8f871ea7a4578e8d334ffb5b1e93f9c81953de673e6c712</ID>
  </Owner>
  <AccessControlList>
    <Grant>
      <Grantee xmlns:xsi="http://www.w3.org/2001/XMLSchema-instance" 
               xsi:type="Canonical User">
        <ID>1f0889cd34796acfd8f871ea7a4578e8d334ffb5b1e93f9c81953de673e6c712</ID>
      </Grantee>
      <Permission>FULL_CONTROL</Permission>
    </Grant>
  </AccessControlList>
</AccessControlPolicy> 